<?xml version="1.0" encoding="utf-8"?>
<?xml-stylesheet href="urn:x-suse:xslt:profiling:docbook51-profile.xsl"
    type="text/xml"
    title="Profiling step"
?>
<!DOCTYPE set
[
   <!ENTITY % entities SYSTEM "entity-decl.ent">
   %entities;
]>


<!--
*********************************
Please see LICENSE.txt for this document's license.
*********************************
-->
<set xmlns="http://docbook.org/ns/docbook" xmlns:xi="http://www.w3.org/2001/XInclude" xmlns:xlink="http://www.w3.org/1999/xlink" version="5.1" xml:lang="pt-br" xml:id="THE-WHOLE-DOCUMENT"><?dbhtml filename="index.html"?><title>Documentação do <phrase role="productname"><phrase os="sled">SUSE Linux Enterprise Desktop</phrase></phrase></title><info><productname><phrase role="productname"><phrase os="sled">SUSE Linux Enterprise Desktop</phrase></phrase></productname><productnumber><phrase role="productname"><phrase os="sles;sled;slerte">11 SP4</phrase></phrase></productnumber></info>
 



 






 <xi:include href="book_sle_admin.xml" parse="xml"/>

 <xi:include href="book_sle_deployment.xml" parse="xml"/>

 

 <xi:include href="book_security.xml" parse="xml"/>

 <xi:include href="book_sles_xen.xml" parse="xml"/>

 <xi:include href="book_sle_tuning.xml" parse="xml"/>






 

 

 






 <xi:include os="sled" href="book_kdeuser.xml" parse="xml"/>

 <xi:include os="sled" href="book_gnomeuser.xml" parse="xml"/>

 <xi:include os="sled" href="book_application.xml" parse="xml"/>





 <xi:include href="book_quickstarts.xml" parse="xml"/>
</set>
